topsis_simran_102303638/__init__.py
topsis_simran_102303638/topsis_102303638_py.py
topsis_simran_102303638-0.0.2.dist-info/licenses/LICENSE
topsis_simran_102303638-0.0.2.dist-info/METADATA
topsis_simran_102303638-0.0.2.dist-info/WHEEL
topsis_simran_102303638-0.0.2.dist-info/entry_points.txt
topsis_simran_102303638-0.0.2.dist-info/top_level.txt
topsis_simran_102303638-0.0.2.dist-info/RECORD
