Metadata-Version: 2.4
Name: topsis-simran-102303638
Version: 0.0.2
Summary: TOPSIS implementation as a CLI tool
Author: Simran Kaur
Author-email: kaursimran789812@gmail.com
Requires-Python: >=3.6
License-File: LICENSE
Dynamic: author
Dynamic: author-email
Dynamic: description
Dynamic: description-content-type
Dynamic: license-file
Dynamic: requires-python
Dynamic: summary
